{
  "version": "0.1.0",
  "canon": "v15.7",
  "mode": "phase0-audit",
  "fixture_pack": "integration-paths",
  "notes": [
    "This pack starts the integration corpus class required by the v15.7 coverage contract.",
    "The goal is not final program-end integration yet, but canonical public-path proof that multiple process families now co-exist in one solved case.",
    "These fixtures are still Phase 0 scaffolds and should not be mistaken for the final modern validation corpus."
  ],
  "fixtures": [
    {
      "id": "FX-INT-01",
      "row": "RELATION_TRIAD",
      "kind": "single",
      "fixture_class": "integration",
      "purpose": "Canonical runtime should expose integrated relation, face, order, distributed Leg, field, failure, envelope, and cascade outputs in one solved case.",
      "assertions": [
        "validate_ok",
        "solve_ok",
        "path_exists:timeline.0.participants.p2.solver_debug.relation_summary.faces",
        "path_exists:timeline.0.participants.p2.solver_debug.relation_summary.order_notes",
        "path_exists:timeline.0.participants.p2.solver_debug.relation_summary.leg_scopes",
        "path_exists:timeline.0.participants.p2.solver_debug.relation_summary.field_scopes",
        "path_exists:timeline.0.participants.p2.failure.primary",
        "path_exists:timeline.0.participants.p2.envelope.status",
        "path_exists:timeline.0.participants.p2.cascade.primary_failure"
      ],
      "case_data": {
        "system_name": "fx-int-01-integrated-runtime-path",
        "participants": [{ "id": "p1", "name": "P1" }, { "id": "p2", "name": "P2" }, { "id": "p3", "name": "P3" }],
        "timeline": [{ "timestep_label": "T0", "participants": { "p1": { "axes": { "Cfg": { "A": 82, "R": 82, "I": 82, "sigma": "L" }, "Emb": { "A": 80, "R": 80, "I": 80, "sigma": "L" }, "Org": { "A": 81, "R": 81, "I": 81, "sigma": "L" }, "Dir": { "A": 84, "R": 84, "I": 84, "sigma": "L" }, "Leg": { "A": 80, "R": 80, "I": 80, "sigma": "L" } } }, "p2": { "cascade": { "attempts": [{ "axis": "Cfg" }, { "axis": "Org" }, { "axis": "Leg" }] }, "axes": { "Cfg": { "A": 22, "R": 30, "I": 82, "sigma": "L" }, "Emb": { "A": 58, "R": 58, "I": 60, "sigma": "L" }, "Org": { "A": 62, "R": 62, "I": 66, "sigma": "L" }, "Dir": { "A": 38, "R": 42, "I": 78, "sigma": "L" }, "Leg": { "A": 64, "R": 64, "I": 66, "sigma": "L" } } }, "p3": { "axes": { "Cfg": { "A": 24, "R": 30, "I": 82, "sigma": "M" }, "Emb": { "A": 30, "R": 34, "I": 78, "sigma": "M" }, "Org": { "A": 22, "R": 30, "I": 88, "sigma": "M" }, "Dir": { "A": 26, "R": 32, "I": 84, "sigma": "M" }, "Leg": { "A": 28, "R": 34, "I": 80, "sigma": "M" } } } } }],
        "payload_events": [
          { "timestep_idx": 0, "face": "inner", "scan_index": 1, "order_depth": 3, "leg_scope": "distributed", "trace_persistence": 2, "distributed_span": 3, "alpha_source": "p1.Dir", "alpha_medium": "p3.Org", "alpha_receiving": "p2.Leg", "sigma": "L", "axis": "Leg", "unfolding": "acute", "register": "retained", "mode": "threshold-transfer", "magnitude": 0.62 },
          { "timestep_idx": 0, "face": "outer", "scan_index": 2, "order_depth": 2, "leg_scope": "distributed", "trace_persistence": 2, "distributed_span": 2, "field_scope": "recursive", "field_feedback": 3, "field_depth": 3, "alpha_source": "p1.Org", "alpha_medium": "p3.Org", "alpha_receiving": "p2.Org", "sigma": "M", "axis": "Org", "unfolding": "acute", "register": "retained", "mode": "load", "magnitude": 0.58 }
        ],
        "analysis": { "key_finding": "Integrated public-path seed across relation, face, order, distributed Leg, field, and projection outputs." }
      }
    },
    {
      "id": "FX-INT-02",
      "row": "FIELD_RECURSION",
      "kind": "single",
      "fixture_class": "integration",
      "purpose": "Canonical runtime should expose integrated order, distributed Leg, and recursive field outputs together in one field-facing solved case.",
      "assertions": [
        "validate_ok",
        "solve_ok",
        "path_exists:timeline.0.participants.p2.solver_debug.relation_summary.order_notes",
        "path_exists:timeline.0.participants.p2.solver_debug.relation_summary.leg_scopes",
        "path_exists:timeline.0.participants.p2.solver_debug.relation_summary.field_scopes",
        "path_exists:timeline.0.participants.p2.solver_debug.relation_summary.average_order_depth",
        "path_exists:timeline.0.participants.p2.solver_debug.relation_summary.average_distributed_span",
        "path_exists:timeline.0.participants.p2.solver_debug.relation_summary.average_field_signal",
        "path_exists:timeline.0.participants.p2.envelope.status",
        "path_exists:timeline.0.participants.p2.cascade.projection_mode"
      ],
      "case_data": {
        "system_name": "fx-int-02-field-order-leg-integration",
        "participants": [{ "id": "p1", "name": "P1" }, { "id": "p2", "name": "P2" }, { "id": "p3", "name": "P3" }],
        "timeline": [{ "timestep_label": "T0", "participants": { "p1": { "axes": { "Cfg": { "A": 82, "R": 82, "I": 82, "sigma": "L" }, "Emb": { "A": 80, "R": 80, "I": 80, "sigma": "L" }, "Org": { "A": 81, "R": 81, "I": 81, "sigma": "L" }, "Dir": { "A": 84, "R": 84, "I": 84, "sigma": "L" }, "Leg": { "A": 80, "R": 80, "I": 80, "sigma": "L" } } }, "p2": { "cascade": { "attempts": [{ "axis": "Org" }, { "axis": "Leg" }, { "axis": "Cfg" }] }, "axes": { "Cfg": { "A": 24, "R": 30, "I": 82, "sigma": "L" }, "Emb": { "A": 58, "R": 58, "I": 60, "sigma": "L" }, "Org": { "A": 60, "R": 60, "I": 68, "sigma": "L" }, "Dir": { "A": 38, "R": 42, "I": 78, "sigma": "L" }, "Leg": { "A": 62, "R": 62, "I": 68, "sigma": "L" } } }, "p3": { "axes": { "Cfg": { "A": 22, "R": 28, "I": 84, "sigma": "M" }, "Emb": { "A": 30, "R": 34, "I": 78, "sigma": "M" }, "Org": { "A": 20, "R": 30, "I": 88, "sigma": "M" }, "Dir": { "A": 26, "R": 32, "I": 84, "sigma": "M" }, "Leg": { "A": 28, "R": 34, "I": 80, "sigma": "M" } } } } }],
        "payload_events": [
          { "timestep_idx": 0, "face": "inner", "scan_index": 1, "order_depth": 4, "leg_scope": "distributed", "trace_persistence": 3, "distributed_span": 3, "alpha_source": "p1.Dir", "alpha_medium": "p3.Org", "alpha_receiving": "p2.Leg", "sigma": "L", "axis": "Leg", "unfolding": "acute", "register": "retained", "mode": "threshold-transfer", "magnitude": 0.64 },
          { "timestep_idx": 0, "face": "inner", "scan_index": 2, "order_depth": 3, "leg_scope": "distributed", "trace_persistence": 2, "distributed_span": 2, "field_scope": "recursive", "field_feedback": 4, "field_depth": 3, "alpha_source": "p1.Org", "alpha_medium": "p3.Org", "alpha_receiving": "p2.Org", "sigma": "L", "axis": "Org", "unfolding": "acute", "register": "retained", "mode": "load", "magnitude": 0.60 }
        ],
        "analysis": { "key_finding": "Integrated field/order/Leg-facing public-path seed." }
      }
    },
    {
      "id": "FX-INT-03",
      "row": "ORDER_RECURSION",
      "kind": "single",
      "fixture_class": "integration",
      "purpose": "Canonical runtime should expose integrated order, face, distributed Leg, field recursion, envelope, and cascade outputs in one order-facing solved case.",
      "assertions": [
        "validate_ok",
        "solve_ok",
        "path_exists:timeline.0.participants.p2.solver_debug.relation_summary.order_notes",
        "path_exists:timeline.0.participants.p2.solver_debug.relation_summary.average_order_depth",
        "path_exists:timeline.0.participants.p2.solver_debug.relation_summary.faces",
        "path_exists:timeline.0.participants.p2.solver_debug.relation_summary.leg_scopes",
        "path_exists:timeline.0.participants.p2.solver_debug.relation_summary.field_scopes",
        "path_exists:timeline.0.participants.p2.failure.primary",
        "path_exists:timeline.0.participants.p2.envelope.status",
        "path_exists:timeline.0.participants.p2.cascade.projection_mode"
      ],
      "case_data": {
        "system_name": "fx-int-03-order-facing-integration",
        "participants": [{ "id": "p1", "name": "P1" }, { "id": "p2", "name": "P2" }, { "id": "p3", "name": "P3" }],
        "timeline": [{ "timestep_label": "T0", "participants": { "p1": { "axes": { "Cfg": { "A": 82, "R": 82, "I": 82, "sigma": "L" }, "Emb": { "A": 80, "R": 80, "I": 80, "sigma": "L" }, "Org": { "A": 81, "R": 81, "I": 81, "sigma": "L" }, "Dir": { "A": 84, "R": 84, "I": 84, "sigma": "L" }, "Leg": { "A": 80, "R": 80, "I": 80, "sigma": "L" } } }, "p2": { "cascade": { "attempts": [{ "axis": "Leg" }, { "axis": "Org" }, { "axis": "Cfg" }] }, "axes": { "Cfg": { "A": 24, "R": 30, "I": 82, "sigma": "L" }, "Emb": { "A": 58, "R": 58, "I": 60, "sigma": "L" }, "Org": { "A": 60, "R": 60, "I": 68, "sigma": "L" }, "Dir": { "A": 36, "R": 40, "I": 78, "sigma": "L" }, "Leg": { "A": 62, "R": 62, "I": 68, "sigma": "L" } } }, "p3": { "axes": { "Cfg": { "A": 22, "R": 28, "I": 84, "sigma": "M" }, "Emb": { "A": 30, "R": 34, "I": 78, "sigma": "M" }, "Org": { "A": 20, "R": 30, "I": 88, "sigma": "M" }, "Dir": { "A": 26, "R": 32, "I": 84, "sigma": "M" }, "Leg": { "A": 28, "R": 34, "I": 80, "sigma": "M" } } } } }],
        "payload_events": [
          { "timestep_idx": 0, "face": "inner", "scan_index": 1, "order_depth": 4, "leg_scope": "distributed", "trace_persistence": 3, "distributed_span": 3, "alpha_source": "p1.Dir", "alpha_medium": "p3.Org", "alpha_receiving": "p2.Leg", "sigma": "L", "axis": "Leg", "unfolding": "acute", "register": "retained", "mode": "threshold-transfer", "magnitude": 0.64 },
          { "timestep_idx": 0, "face": "outer", "scan_index": 3, "order_depth": 2, "leg_scope": "distributed", "trace_persistence": 2, "distributed_span": 2, "field_scope": "recursive", "field_feedback": 3, "field_depth": 2, "alpha_source": "p1.Org", "alpha_medium": "p3.Org", "alpha_receiving": "p2.Org", "sigma": "M", "axis": "Org", "unfolding": "acute", "register": "retained", "mode": "load", "magnitude": 0.56 }
        ],
        "analysis": { "key_finding": "Integrated order-facing public-path seed." }
      }
    },
    {
      "id": "FX-INT-04",
      "row": "LEG_DISTRIBUTED",
      "kind": "single",
      "fixture_class": "integration",
      "purpose": "Canonical runtime should expose integrated distributed Leg, face, order, field recursion, envelope, and cascade outputs together in one Leg-facing solved case.",
      "assertions": [
        "validate_ok",
        "solve_ok",
        "path_exists:timeline.0.participants.p2.solver_debug.relation_summary.leg_scopes",
        "path_exists:timeline.0.participants.p2.solver_debug.relation_summary.average_trace_persistence",
        "path_exists:timeline.0.participants.p2.solver_debug.relation_summary.average_distributed_span",
        "path_exists:timeline.0.participants.p2.solver_debug.relation_summary.faces",
        "path_exists:timeline.0.participants.p2.solver_debug.relation_summary.order_notes",
        "path_exists:timeline.0.participants.p2.solver_debug.relation_summary.field_scopes",
        "path_exists:timeline.0.participants.p2.envelope.status",
        "path_exists:timeline.0.participants.p2.cascade.projection_mode"
      ],
      "case_data": {
        "system_name": "fx-int-04-leg-facing-integration",
        "participants": [{ "id": "p1", "name": "P1" }, { "id": "p2", "name": "P2" }, { "id": "p3", "name": "P3" }],
        "timeline": [{ "timestep_label": "T0", "participants": { "p1": { "axes": { "Cfg": { "A": 82, "R": 82, "I": 82, "sigma": "L" }, "Emb": { "A": 80, "R": 80, "I": 80, "sigma": "L" }, "Org": { "A": 81, "R": 81, "I": 81, "sigma": "L" }, "Dir": { "A": 84, "R": 84, "I": 84, "sigma": "L" }, "Leg": { "A": 80, "R": 80, "I": 80, "sigma": "L" } } }, "p2": { "cascade": { "attempts": [{ "axis": "Leg" }, { "axis": "Org" }, { "axis": "Cfg" }] }, "axes": { "Cfg": { "A": 24, "R": 30, "I": 82, "sigma": "L" }, "Emb": { "A": 58, "R": 58, "I": 60, "sigma": "L" }, "Org": { "A": 60, "R": 60, "I": 68, "sigma": "L" }, "Dir": { "A": 36, "R": 40, "I": 78, "sigma": "L" }, "Leg": { "A": 62, "R": 62, "I": 68, "sigma": "L" } } }, "p3": { "axes": { "Cfg": { "A": 22, "R": 28, "I": 84, "sigma": "M" }, "Emb": { "A": 30, "R": 34, "I": 78, "sigma": "M" }, "Org": { "A": 20, "R": 30, "I": 88, "sigma": "M" }, "Dir": { "A": 26, "R": 32, "I": 84, "sigma": "M" }, "Leg": { "A": 28, "R": 34, "I": 80, "sigma": "M" } } } } }],
        "payload_events": [
          { "timestep_idx": 0, "face": "inner", "scan_index": 1, "order_depth": 3, "leg_scope": "distributed", "trace_persistence": 4, "distributed_span": 3, "alpha_source": "p1.Dir", "alpha_medium": "p3.Org", "alpha_receiving": "p2.Leg", "sigma": "L", "axis": "Leg", "unfolding": "acute", "register": "retained", "mode": "threshold-transfer", "magnitude": 0.66 },
          { "timestep_idx": 0, "face": "inner", "scan_index": 2, "order_depth": 2, "leg_scope": "distributed", "trace_persistence": 2, "distributed_span": 2, "field_scope": "recursive", "field_feedback": 3, "field_depth": 2, "alpha_source": "p1.Org", "alpha_medium": "p3.Org", "alpha_receiving": "p2.Org", "sigma": "L", "axis": "Org", "unfolding": "acute", "register": "retained", "mode": "load", "magnitude": 0.58 }
        ],
        "analysis": { "key_finding": "Integrated Leg-facing public-path seed." }
      }
    },
    {
      "id": "FX-INT-05",
      "row": "THRESHOLD_PREVALENCE",
      "kind": "single",
      "fixture_class": "integration",
      "purpose": "Canonical runtime should expose integrated mirrored threshold, relation, face, order, distributed Leg, field recursion, envelope, and cascade outputs in one threshold-facing solved case.",
      "assertions": [
        "validate_ok",
        "solve_ok",
        "path_exists:timeline.0.participants.p2.prevalence",
        "path_exists:timeline.0.participants.p2.theta",
        "path_exists:timeline.0.participants.p2.solver_debug.cfg_gate",
        "path_exists:timeline.0.participants.p2.solver_debug.relation_summary.faces",
        "path_exists:timeline.0.participants.p2.solver_debug.relation_summary.order_notes",
        "path_exists:timeline.0.participants.p2.solver_debug.relation_summary.leg_scopes",
        "path_exists:timeline.0.participants.p2.solver_debug.relation_summary.field_scopes",
        "path_exists:timeline.0.participants.p2.envelope.status",
        "path_exists:timeline.0.participants.p2.cascade.projection_mode"
      ],
      "case_data": {
        "system_name": "fx-int-05-threshold-facing-integration",
        "participants": [{ "id": "p1", "name": "P1" }, { "id": "p2", "name": "P2" }, { "id": "p3", "name": "P3" }],
        "timeline": [{ "timestep_label": "T0", "participants": { "p1": { "axes": { "Cfg": { "A": 82, "R": 82, "I": 82, "sigma": "L" }, "Emb": { "A": 80, "R": 80, "I": 80, "sigma": "L" }, "Org": { "A": 81, "R": 81, "I": 81, "sigma": "L" }, "Dir": { "A": 84, "R": 84, "I": 84, "sigma": "L" }, "Leg": { "A": 80, "R": 80, "I": 80, "sigma": "L" } } }, "p2": { "cascade": { "attempts": [{ "axis": "Cfg" }, { "axis": "Leg" }, { "axis": "Org" }] }, "axes": { "Cfg": { "A": 22, "R": 30, "I": 82, "sigma": "L" }, "Emb": { "A": 58, "R": 58, "I": 60, "sigma": "L" }, "Org": { "A": 62, "R": 62, "I": 66, "sigma": "L" }, "Dir": { "A": 36, "R": 40, "I": 78, "sigma": "L" }, "Leg": { "A": 72, "R": 72, "I": 74, "sigma": "L" } } }, "p3": { "axes": { "Cfg": { "A": 28, "R": 34, "I": 82, "sigma": "M" }, "Emb": { "A": 32, "R": 35, "I": 78, "sigma": "M" }, "Org": { "A": 22, "R": 30, "I": 88, "sigma": "M" }, "Dir": { "A": 26, "R": 32, "I": 84, "sigma": "M" }, "Leg": { "A": 30, "R": 36, "I": 80, "sigma": "M" } } } } }],
        "payload_events": [
          { "timestep_idx": 0, "face": "inner", "scan_index": 1, "order_depth": 3, "leg_scope": "distributed", "trace_persistence": 2, "distributed_span": 3, "alpha_source": "p1.Dir", "alpha_medium": "p3.Org", "alpha_receiving": "p2.Leg", "sigma": "L", "axis": "Leg", "unfolding": "acute", "register": "retained", "mode": "threshold-transfer", "magnitude": 0.60 },
          { "timestep_idx": 0, "face": "inner", "scan_index": 2, "order_depth": 2, "leg_scope": "distributed", "trace_persistence": 2, "distributed_span": 2, "field_scope": "recursive", "field_feedback": 3, "field_depth": 2, "alpha_source": "p1.Org", "alpha_medium": "p3.Org", "alpha_receiving": "p2.Org", "sigma": "L", "axis": "Org", "unfolding": "acute", "register": "retained", "mode": "load", "magnitude": 0.56 }
        ],
        "analysis": { "key_finding": "Integrated threshold-facing public-path seed." }
      }
    },
    {
      "id": "FX-INT-06",
      "row": "FAMILY_TRUTH",
      "kind": "single",
      "fixture_class": "integration",
      "purpose": "Canonical runtime should expose integrated family-truth, mirrored threshold, relation, face, order, distributed Leg, recursive field, envelope, and cascade outputs in one family-facing solved case.",
      "assertions": [
        "validate_ok",
        "solve_ok",
        "path_exists:timeline.0.participants.p2.prevalence",
        "path_exists:timeline.0.participants.p2.theta",
        "path_exists:timeline.0.participants.p2.solver_debug.relation_summary.faces",
        "path_exists:timeline.0.participants.p2.solver_debug.relation_summary.order_notes",
        "path_exists:timeline.0.participants.p2.solver_debug.relation_summary.leg_scopes",
        "path_exists:timeline.0.participants.p2.solver_debug.relation_summary.field_scopes",
        "path_exists:timeline.0.participants.p2.envelope.status",
        "path_exists:timeline.0.participants.p2.cascade.projection_mode"
      ],
      "case_data": {
        "system_name": "fx-int-06-family-facing-integration",
        "participants": [{ "id": "p1", "name": "P1" }, { "id": "p2", "name": "P2" }, { "id": "p3", "name": "P3" }],
        "timeline": [{ "timestep_label": "T0", "participants": { "p1": { "axes": { "Cfg": { "A": 82, "R": 82, "I": 82, "sigma": "L" }, "Emb": { "A": 80, "R": 80, "I": 80, "sigma": "L" }, "Org": { "A": 81, "R": 81, "I": 81, "sigma": "L" }, "Dir": { "A": 84, "R": 84, "I": 84, "sigma": "L" }, "Leg": { "A": 80, "R": 80, "I": 80, "sigma": "L" } } }, "p2": { "cascade": { "attempts": [{ "axis": "Cfg" }, { "axis": "Leg" }, { "axis": "Org" }] }, "axes": { "Cfg": { "A": 22, "R": 30, "I": 82, "sigma": "L" }, "Emb": { "A": 58, "R": 58, "I": 60, "sigma": "L" }, "Org": { "A": 70, "R": 70, "I": 72, "sigma": "L" }, "Dir": { "A": 36, "R": 40, "I": 78, "sigma": "L" }, "Leg": { "A": 72, "R": 72, "I": 74, "sigma": "L" } } }, "p3": { "axes": { "Cfg": { "A": 81, "R": 81, "I": 81, "sigma": "L" }, "Emb": { "A": 79, "R": 79, "I": 79, "sigma": "L" }, "Org": { "A": 82, "R": 82, "I": 82, "sigma": "L" }, "Dir": { "A": 80, "R": 80, "I": 80, "sigma": "L" }, "Leg": { "A": 79, "R": 79, "I": 79, "sigma": "L" } } } } }],
        "payload_events": [
          { "timestep_idx": 0, "face": "inner", "scan_index": 1, "order_depth": 3, "leg_scope": "distributed", "trace_persistence": 2, "distributed_span": 3, "alpha_source": "p1.Dir", "alpha_medium": "p1.Org", "alpha_receiving": "p2.Leg", "sigma": "L", "axis": "Leg", "unfolding": "acute", "register": "retained", "mode": "threshold-transfer", "magnitude": 0.58 },
          { "timestep_idx": 0, "face": "inner", "scan_index": 2, "order_depth": 2, "leg_scope": "distributed", "trace_persistence": 1, "distributed_span": 2, "field_scope": "recursive", "field_feedback": 3, "field_depth": 2, "alpha_source": "p1.Org", "alpha_medium": "p3.Org", "alpha_receiving": "p2.Org", "sigma": "L", "axis": "Org", "unfolding": "acute", "register": "retained", "mode": "load", "magnitude": 0.54 }
        ],
        "analysis": { "key_finding": "Integrated family-facing public-path seed." }
      }
    },
    {
      "id": "FX-INT-07",
      "row": "FAILURE_OVERFLOW",
      "kind": "single",
      "fixture_class": "integration",
      "purpose": "Canonical runtime should expose integrated overflow failure grammar, relation, face, order, distributed Leg, recursive field, envelope, compensation, and cascade outputs in one overflow-facing solved case.",
      "assertions": [
        "validate_ok",
        "solve_ok",
        "path_exists:timeline.0.participants.p2.failure.primary",
        "path_exists:timeline.0.participants.p2.failure.grammars.overflow",
        "path_exists:timeline.0.participants.p2.solver_debug.relation_summary.faces",
        "path_exists:timeline.0.participants.p2.solver_debug.relation_summary.order_notes",
        "path_exists:timeline.0.participants.p2.solver_debug.relation_summary.leg_scopes",
        "path_exists:timeline.0.participants.p2.solver_debug.relation_summary.field_scopes",
        "path_exists:timeline.0.participants.p2.envelope.status",
        "path_exists:timeline.0.participants.p2.compensation",
        "path_exists:timeline.0.participants.p2.cascade.projection_mode"
      ],
      "case_data": {
        "system_name": "fx-int-07-overflow-facing-integration",
        "participants": [{ "id": "p1", "name": "P1" }, { "id": "p2", "name": "P2" }, { "id": "p3", "name": "P3" }],
        "timeline": [{ "timestep_label": "T0", "participants": { "p1": { "axes": { "Cfg": { "A": 82, "R": 82, "I": 82, "sigma": "L" }, "Emb": { "A": 79, "R": 79, "I": 79, "sigma": "L" }, "Org": { "A": 81, "R": 81, "I": 81, "sigma": "L" }, "Dir": { "A": 84, "R": 84, "I": 84, "sigma": "L" }, "Leg": { "A": 80, "R": 80, "I": 80, "sigma": "L" } } }, "p2": { "cascade": { "attempts": [{ "axis": "Cfg" }, { "axis": "Dir" }, { "axis": "Leg" }, { "axis": "Org" }] }, "axes": { "Cfg": { "A": 24, "R": 34, "I": 76, "sigma": "L" }, "Emb": { "A": 45, "R": 45, "I": 62, "sigma": "L" }, "Org": { "A": 52, "R": 52, "I": 64, "sigma": "L" }, "Dir": { "A": 38, "R": 38, "I": 68, "sigma": "L" }, "Leg": { "A": 36, "R": 36, "I": 64, "sigma": "L" } } }, "p3": { "axes": { "Cfg": { "A": 78, "R": 78, "I": 78, "sigma": "L" }, "Emb": { "A": 77, "R": 77, "I": 77, "sigma": "L" }, "Org": { "A": 80, "R": 80, "I": 80, "sigma": "L" }, "Dir": { "A": 76, "R": 76, "I": 76, "sigma": "L" }, "Leg": { "A": 75, "R": 75, "I": 75, "sigma": "L" } } } } }],
        "payload_events": [
          { "timestep_idx": 0, "face": "inner", "scan_index": 1, "order_depth": 3, "leg_scope": "distributed", "trace_persistence": 2, "distributed_span": 3, "alpha_source": "p1.Dir", "alpha_medium": "p3.Org", "alpha_receiving": "p2.Leg", "sigma": "M", "axis": "Leg", "unfolding": "acute", "register": "retained", "mode": "overflow", "magnitude": 0.90 },
          { "timestep_idx": 0, "face": "outer", "scan_index": 2, "order_depth": 2, "leg_scope": "distributed", "trace_persistence": 2, "distributed_span": 2, "field_scope": "recursive", "field_feedback": 3, "field_depth": 2, "alpha_source": "p1.Org", "alpha_medium": "p3.Org", "alpha_receiving": "p2.Org", "sigma": "L", "axis": "Org", "unfolding": "acute", "register": "retained", "mode": "overflow", "magnitude": 0.80 },
          { "timestep_idx": 0, "face": "inner", "scan_index": 3, "order_depth": 2, "leg_scope": "distributed", "trace_persistence": 1, "distributed_span": 2, "alpha_source": "p1.Cfg", "alpha_medium": "p3.Cfg", "alpha_receiving": "p2.Cfg", "sigma": "M", "axis": "Cfg", "unfolding": "acute", "register": "retained", "mode": "overflow", "magnitude": 0.85 }
        ],
        "analysis": { "key_finding": "Integrated overflow-facing public-path seed." }
      }
    }
  ]
}
